test/__init__.py
test/test_client.py
test/test_oauth.py
test/utilities.py
test/resources/__init__.py
test/resources/test_layout.py
test/resources/test_record.py
test/utils/__init__.py
test/utils/test_client_utils.py
zoho_somconnexio_python_client/__init__.py
zoho_somconnexio_python_client/client.py
zoho_somconnexio_python_client/exceptions.py
zoho_somconnexio_python_client/oauth.py
zoho_somconnexio_python_client/resources/__init__.py
zoho_somconnexio_python_client/resources/layout.py
zoho_somconnexio_python_client/resources/record.py
zoho_somconnexio_python_client/utils/__init__.py
zoho_somconnexio_python_client/utils/client_utils.py
zoho_somconnexio_python_client-0.1.2.dist-info/METADATA
zoho_somconnexio_python_client-0.1.2.dist-info/WHEEL
zoho_somconnexio_python_client-0.1.2.dist-info/top_level.txt
zoho_somconnexio_python_client-0.1.2.dist-info/RECORD
