Metadata-Version: 2.1
Name: zoho-somconnexio-python-client
Version: 0.1.2
Summary: Python wrapper for SomConnexio's Zoho (using REST API)
Home-page: https://git.coopdevs.org/coopdevs/som-connexio/zoho/zoho-somconnexio-python-client
Author: SomConnexio
Author-email: borja.gimeno@somconnexio.coop
Maintainer: Borja Gimeno
Classifier: Development Status :: 3 - Alpha
Classifier: Operating System :: POSIX :: Linux
Classifier: Programming Language :: Python :: 3.11
Requires-Dist: requests
